listfunc/__init__.py
listfunc/listfunc.py
listfunc-1.0.0.dist-info/LICENSE
listfunc-1.0.0.dist-info/METADATA
listfunc-1.0.0.dist-info/WHEEL
listfunc-1.0.0.dist-info/top_level.txt
listfunc-1.0.0.dist-info/RECORD
